{ 
   "name":"",
   "children":[ 
      { 
         "name":"",
         "children":[ 
            { 
               "name":"1",
               "children":[ 
                  { 
                     "name":"11",
                     "children":[ 
                        { 
                           "name":"111",
                           "children":[ 
                              { 
                                 "name":"1111",
                                 "children":[ 
                                    { 
                                       "name":"11111",
                                       "children":[ 

                                       ]
                                    },
                                    { 
                                       "name":"11112",
                                       "children":[ 

                                       ]
                                    }
                                 ]
                              },
                              { 
                                 "name":"1112",
                                 "children":[ 
                                    { 
                                       "name":"11121",
                                       "children":[ 

                                       ]
                                    },
                                    { 
                                       "name":"11122",
                                       "children":[ 

                                       ]
                                    }
                                 ]
                              }
                           ]
                        },
                        { 
                           "name":"112",
                           "children":[ 
                              { 
                                 "name":"1121",
                                 "children":[ 
                                    { 
                                       "name":"11211",
                                       "children":[ 

                                       ]
                                    },
                                    { 
                                       "name":"11212",
                                       "children":[ 

                                       ]
                                    }
                                 ]
                              },
                              { 
                                 "name":"1122",
                                 "children":[ 
                                    { 
                                       "name":"11221",
                                       "children":[ 

                                       ]
                                    },
                                    { 
                                       "name":"11222",
                                       "children":[ 

                                       ]
                                    }
                                 ]
                              }
                           ]
                        }
                     ]
                  },
                  { 
                     "name":"12",
                     "children":[ 
                        { 
                           "name":"121",
                           "children":[ 
                              { 
                                 "name":"1211",
                                 "children":[ 
                                    { 
                                       "name":"12111",
                                       "children":[ 

                                       ]
                                    },
                                    { 
                                       "name":"12112",
                                       "children":[ 

                                       ]
                                    }
                                 ]
                              },
                              { 
                                 "name":"1212",
                                 "children":[ 
                                    { 
                                       "name":"12121",
                                       "children":[ 

                                       ]
                                    },
                                    { 
                                       "name":"12122",
                                       "children":[ 

                                       ]
                                    }
                                 ]
                              }
                           ]
                        },
                        { 
                           "name":"122",
                           "children":[ 
                              { 
                                 "name":"1221",
                                 "children":[ 
                                    { 
                                       "name":"12211",
                                       "children":[ 

                                       ]
                                    },
                                    { 
                                       "name":"12212",
                                       "children":[ 

                                       ]
                                    }
                                 ]
                              },
                              { 
                                 "name":"1222",
                                 "children":[ 
                                    { 
                                       "name":"12221",
                                       "children":[ 

                                       ]
                                    },
                                    { 
                                       "name":"12222",
                                       "children":[ 

                                       ]
                                    }
                                 ]
                              }
                           ]
                        }
                     ]
                  }
               ]
            },
            { 
               "name":"2",
               "children":[ 
                  { 
                     "name":"21",
                     "children":[ 
                        { 
                           "name":"211",
                           "children":[ 
                              { 
                                 "name":"2111",
                                 "children":[ 
                                    { 
                                       "name":"21111",
                                       "children":[ 

                                       ]
                                    },
                                    { 
                                       "name":"21112",
                                       "children":[ 

                                       ]
                                    }
                                 ]
                              },
                              { 
                                 "name":"2112",
                                 "children":[ 
                                    { 
                                       "name":"21121",
                                       "children":[ 

                                       ]
                                    },
                                    { 
                                       "name":"21122",
                                       "children":[ 

                                       ]
                                    }
                                 ]
                              }
                           ]
                        },
                        { 
                           "name":"212",
                           "children":[ 
                              { 
                                 "name":"2121",
                                 "children":[ 
                                    { 
                                       "name":"21211",
                                       "children":[ 

                                       ]
                                    },
                                    { 
                                       "name":"21212",
                                       "children":[ 

                                       ]
                                    }
                                 ]
                              },
                              { 
                                 "name":"2122",
                                 "children":[ 
                                    { 
                                       "name":"21221",
                                       "children":[ 

                                       ]
                                    },
                                    { 
                                       "name":"21222",
                                       "children":[ 

                                       ]
                                    }
                                 ]
                              }
                           ]
                        }
                     ]
                  },
                  { 
                     "name":"22",
                     "children":[ 
                        { 
                           "name":"221",
                           "children":[ 
                              { 
                                 "name":"2211",
                                 "children":[ 
                                    { 
                                       "name":"22111",
                                       "children":[ 

                                       ]
                                    },
                                    { 
                                       "name":"22112",
                                       "children":[ 

                                       ]
                                    }
                                 ]
                              },
                              { 
                                 "name":"2212",
                                 "children":[ 
                                    { 
                                       "name":"22121",
                                       "children":[ 

                                       ]
                                    },
                                    { 
                                       "name":"22122",
                                       "children":[ 

                                       ]
                                    }
                                 ]
                              }
                           ]
                        },
                        { 
                           "name":"222",
                           "children":[ 
                              { 
                                 "name":"2221",
                                 "children":[ 
                                    { 
                                       "name":"22211",
                                       "children":[ 

                                       ]
                                    },
                                    { 
                                       "name":"22212",
                                       "children":[ 

                                       ]
                                    }
                                 ]
                              },
                              { 
                                 "name":"2222",
                                 "children":[ 
                                    { 
                                       "name":"22221",
                                       "children":[ 

                                       ]
                                    },
                                    { 
                                       "name":"22222",
                                       "children":[ 

                                       ]
                                    }
                                 ]
                              }
                           ]
                        }
                     ]
                  }
               ]
            }
         ]
      }
   ]
}
